{"nodes": [{"id": "tests_lib_providerrouter_test_ts", "label": "providerRouter.test.ts", "file_type": "code", "source_file": "tests\\lib\\providerRouter.test.ts", "source_location": "L1"}], "edges": [{"source": "tests_lib_providerrouter_test_ts", "target": "vitest", "relation": "imports_from", "confidence": "EXTRACTED", "source_file": "tests\\lib\\providerRouter.test.ts", "source_location": "L1", "weight": 1.0}, {"source": "tests_lib_providerrouter_test_ts", "target": "providerrouter", "relation": "imports_from", "confidence": "EXTRACTED", "source_file": "tests\\lib\\providerRouter.test.ts", "source_location": "L2", "weight": 1.0}]}